{
    "__comment": "Made with TheDestruc7i0n's advancements generator: https://advancements.thedestruc7i0n.ca",
    "display": {
        "title": {
            "translate": "achievement.robbery",
            "color": "dark_aqua"
        },
        "description": {
            "translate": "achievement.robbery.description",
            "color": "white"
        },
        "icon": {
            "item": "minecraft:ender_eye",
            "nbt": "{CustomModelData:1}"
        },
        "frame": "goal",
        "show_toast": true,
        "announce_to_chat": false,
        "hidden": false
    },
    "criteria": {
        "impossible": {
            "trigger": "minecraft:impossible"
        }
    },
    "parent": "tutorial:zzzunlockables/intruder"
}