{
  "pools": [
    {
      "rolls": 1,
      "entries": [
        {
          "type": "minecraft:item",
          "name": "minecraft:diamond_sword"
        }
      ],
      "functions": [
        {
          "function": "minecraft:set_components",
          "components": {
            "!minecraft:damage": {},
            "minecraft:custom_name": "[{\"translate\":\"item.saber\",\"italic\":false,\"color\":\"dark_aqua\"}]",
            "minecraft:enchantments": {
              "levels": {},
              "show_in_tooltip": false
            }
          }
        },
        {
          "function": "minecraft:set_custom_data",
          "tag": "{NoDrop:1b}",
          "conditions": [
            {
              "condition": "minecraft:entity_properties",
              "entity": "this",
              "predicate": {
                "team": "Lobby"
              }
            }
          ]
        }
      ]
    }
  ]
}
