{
    "condition": "minecraft:entity_properties",
    "entity": "this",
    "predicate": {
        "equipment": {
            "mainhand": {
                "items": "#game:noninteractable"
            },
            "offhand": {
                "items": "minecraft:mooshroom_spawn_egg",
                "components": {
                    "minecraft:max_stack_size": 64
                },
                "predicates": {
                    "minecraft:custom_data": "{CrabTrap:1b}"
                }
            }
        }
    }
}